{
  "scenario": "14 bbs - RFI UTG",
  "bet_size": "Open size: 2bbs (12,1%), Open shove (3%)",
  "hands": [
    {"hand": "AA", "action": "Open", "ev": 7.38, "color": "red"},
    {"hand": "AKs", "action": "Open", "ev": 2.6, "color": "red"},
    {"hand": "AQs", "action": "Open", "ev": 1.6, "color": "red"},
    {"hand": "AJs", "action": "Open", "ev": 0.78, "color": "red"},
    {"hand": "ATs", "action": "Open", "ev": 0.34, "color": "red"},
    {"hand": "A9s", "action": "Open", "ev": 0.14, "color": "red"},
    {"hand": "A8s", "action": "Fold", "ev": 0, "color": "blue"},
    {"hand": "A7s", "action": "Open", "ev": 0.11, "color": "red"},
    {"hand": "A6s", "action": "Fold", "ev": 0, "color": "blue"},
    {"hand": "A5s", "action": "Open", "ev": 0.07, "color": "red"},
    {"hand": "A4s", "action": "Fold", "ev": 0, "color": "blue"},
    {"hand": "A3s", "action": "Fold", "ev": 0, "color": "blue"},
    {"hand": "A2s", "action": "Fold", "ev": 0, "color": "blue"},
    {"hand": "AKo", "action": "Open", "ev": 2.15, "color": "red"},
    {"hand": "KK", "action": "Open", "ev": 5.83, "color": "red"},
    {"hand": "KQs", "action": "Open", "ev": 0.48, "color": "red"},
    {"hand": "KJs", "action": "Open", "ev": 0.21, "color": "red"},
    {"hand": "KTs", "action": "Open", "ev": 0.15, "color": "red"},
    {"hand": "K9s", "action": "Open", "ev": 0.02, "color": "red"},
    {"hand": "K8s", "action": "Fold", "ev": 0, "color": "blue"},
    {"hand": "K7s", "action": "Fold", "ev": 0, "color": "blue"},
    {"hand": "K6s", "action": "Fold", "ev": 0, "color": "blue"},
    {"hand": "K5s", "action": "Fold", "ev": 0, "color": "blue"},
    {"hand": "K4s", "action": "Fold", "ev": 0, "color": "blue"},
    {"hand": "K3s", "action": "Fold", "ev": 0, "color": "blue"},
    {"hand": "K2s", "action": "Fold", "ev": 0, "color": "blue"},
    {"hand": "AQo", "action": "Open", "ev": 1.14, "color": "red"},
    {"hand": "KQo", "action": "Fold", "ev": 0, "color": "blue"},
    {"hand": "QQ", "action": "Open", "ev": 4.22, "color": "red"},
    {"hand": "QJs", "action": "Open", "ev": 0.13, "color": "red"},
    {"hand": "QTs", "action": "Open", "ev": 0.01, "color": "red"},
    {"hand": "Q9s", "action": "Fold", "ev": 0, "color": "blue"},
    {"hand": "Q8s", "action": "Fold", "ev": 0, "color": "blue"},
    {"hand": "Q7s", "action": "Fold", "ev": 0, "color": "blue"},
    {"hand": "Q6s", "action": "Fold", "ev": 0, "color": "blue"},
    {"hand": "Q5s", "action": "Fold", "ev": 0, "color": "blue"},
    {"hand": "Q4s", "action": "Fold", "ev": 0, "color": "blue"},
    {"hand": "Q3s", "action": "Fold", "ev": 0, "color": "blue"},
    {"hand": "Q2s", "action": "Fold", "ev": 0, "color": "blue"},
    {"hand": "AJo", "action": "Open", "ev": 0.3, "color": "red"},
    {"hand": "KJo", "action": "Fold", "ev": 0, "color": "blue"},
    {"hand": "QJo", "action": "Fold", "ev": 0, "color": "blue"},
    {"hand": "JJ", "action": "Open", "ev": 3.03, "color": "red"},
    {"hand": "JTs", "action": "Fold", "ev": 0, "color": "blue"},
    {"hand": "J9s", "action": "Fold", "ev": 0, "color": "blue"},
    {"hand": "J8s", "action": "Fold", "ev": 0, "color": "blue"},
    {"hand": "J7s", "action": "Fold", "ev": 0, "color": "blue"},
    {"hand": "J6s", "action": "Fold", "ev": 0, "color": "blue"},
    {"hand": "J5s", "action": "Fold", "ev": 0, "color": "blue"},
    {"hand": "J4s", "action": "Fold", "ev": 0, "color": "blue"},
    {"hand": "J3s", "action": "Fold", "ev": 0, "color": "blue"},
    {"hand": "J2s", "action": "Fold", "ev": 0, "color": "blue"},
    {"hand": "ATo", "action": "Open", "ev": 0.07, "color": "red"},
    {"hand": "KTo", "action": "Fold", "ev": 0, "color": "blue"},
    {"hand": "QTo", "action": "Fold", "ev": 0, "color": "blue"},
    {"hand": "JTo", "action": "Fold", "ev": 0, "color": "blue"},
    {"hand": "TT", "action": "Open", "ev": 2.09, "color": "red"},
    {"hand": "T9s", "action": "Fold", "ev": 0, "color": "blue"},
    {"hand": "T8s", "action": "Fold", "ev": 0, "color": "blue"},
    {"hand": "T7s", "action": "Fold", "ev": 0, "color": "blue"},
    {"hand": "T6s", "action": "Fold", "ev": 0, "color": "blue"},
    {"hand": "T5s", "action": "Fold", "ev": 0, "color": "blue"},
    {"hand": "T4s", "action": "Fold", "ev": 0, "color": "blue"},
    {"hand": "T3s", "action": "Fold", "ev": 0, "color": "blue"},
    {"hand": "T2s", "action": "Fold", "ev": 0, "color": "blue"},
    {"hand": "A9o", "action": "Fold", "ev": 0, "color": "blue"},
    {"hand": "K9o", "action": "Fold", "ev": 0, "color": "blue"},
    {"hand": "Q9o", "action": "Fold", "ev": 0, "color": "blue"},
    {"hand": "J9o", "action": "Fold", "ev": 0, "color": "blue"},
    {"hand": "T9o", "action": "Fold", "ev": 0, "color": "blue"},
    {"hand": "99", "action": "Open", "ev": 1.32, "color": "red"},
    {"hand": "98s", "action": "Fold", "ev": 0, "color": "blue"},
    {"hand": "97s", "action": "Fold", "ev": 0, "color": "blue"},
    {"hand": "96s", "action": "Fold", "ev": 0, "color": "blue"},
    {"hand": "95s", "action": "Fold", "ev": 0, "color": "blue"},
    {"hand": "94s", "action": "Fold", "ev": 0, "color": "blue"},
    {"hand": "93s", "action": "Fold", "ev": 0, "color": "blue"},
    {"hand": "92s", "action": "Fold", "ev": 0, "color": "blue"},
    {"hand": "A8o", "action": "Fold", "ev": 0, "color": "blue"},
    {"hand": "K8o", "action": "Fold", "ev": 0, "color": "blue"},
    {"hand": "Q8o", "action": "Fold", "ev": 0, "color": "blue"},
    {"hand": "J8o", "action": "Fold", "ev": 0, "color": "blue"},
    {"hand": "T8o", "action": "Fold", "ev": 0, "color": "blue"},
    {"hand": "98o", "action": "Fold", "ev": 0, "color": "blue"},
    {"hand": "88", "action": "Open", "ev": 0.76, "color": "red"},
    {"hand": "87s", "action": "Fold", "ev": 0, "color": "blue"},
    {"hand": "86s", "action": "Fold", "ev": 0, "color": "blue"},
    {"hand": "85s", "action": "Fold", "ev": 0, "color": "blue"},
    {"hand": "84s", "action": "Fold", "ev": 0, "color": "blue"},
    {"hand": "83s", "action": "Fold", "ev": 0, "color": "blue"},
    {"hand": "82s", "action": "Fold", "ev": 0, "color": "blue"},
    {"hand": "A7o", "action": "Fold", "ev": 0, "color": "blue"},
    {"hand": "K7o", "action": "Fold", "ev": 0, "color": "blue"},
    {"hand": "Q7o", "action": "Fold", "ev": 0, "color": "blue"},
    {"hand": "J7o", "action": "Fold", "ev": 0, "color": "blue"},
    {"hand": "T7o", "action": "Fold", "ev": 0, "color": "blue"},
    {"hand": "97o", "action": "Fold", "ev": 0, "color": "blue"},
    {"hand": "87o", "action": "Fold", "ev": 0, "color": "blue"},
    {"hand": "77", "action": "Open", "ev": 0.28, "color": "red"},
    {"hand": "76s", "action": "Fold", "ev": 0, "color": "blue"},
    {"hand": "75s", "action": "Fold", "ev": 0, "color": "blue"},
    {"hand": "74s", "action": "Fold", "ev": 0, "color": "blue"},
    {"hand": "73s", "action": "Fold", "ev": 0, "color": "blue"},
    {"hand": "72s", "action": "Fold", "ev": 0, "color": "blue"},
    {"hand": "A6o", "action": "Fold", "ev": 0, "color": "blue"},
    {"hand": "K6o", "action": "Fold", "ev": 0, "color": "blue"},
    {"hand": "Q6o", "action": "Fold", "ev": 0, "color": "blue"},
    {"hand": "J6o", "action": "Fold", "ev": 0, "color": "blue"},
    {"hand": "T6o", "action": "Fold", "ev": 0, "color": "blue"},
    {"hand": "96o", "action": "Fold", "ev": 0, "color": "blue"},
    {"hand": "86o", "action": "Fold", "ev": 0, "color": "blue"},
    {"hand": "76o", "action": "Fold", "ev": 0, "color": "blue"},
    {"hand": "66", "action": "Open", "ev": 0, "color": "red"},
    {"hand": "65s", "action": "Fold", "ev": 0, "color": "blue"},
    {"hand": "64s", "action": "Fold", "ev": 0, "color": "blue"},
    {"hand": "63s", "action": "Fold", "ev": 0, "color": "blue"},
    {"hand": "62s", "action": "Fold", "ev": 0, "color": "blue"},
    {"hand": "A5o", "action": "Fold", "ev": 0, "color": "blue"},
    {"hand": "K5o", "action": "Fold", "ev": 0, "color": "blue"},
    {"hand": "Q5o", "action": "Fold", "ev": 0, "color": "blue"},
    {"hand": "J5o", "action": "Fold", "ev": 0, "color": "blue"},
    {"hand": "T5o", "action": "Fold", "ev": 0, "color": "blue"},
    {"hand": "95o", "action": "Fold", "ev": 0, "color": "blue"},
    {"hand": "85o", "action": "Fold", "ev": 0, "color": "blue"},
    {"hand": "75o", "action": "Fold", "ev": 0, "color": "blue"},
    {"hand": "65o", "action": "Fold", "ev": 0, "color": "blue"},
    {"hand": "55", "action": "Open", "ev": 0, "color": "red"},
    {"hand": "54s", "action": "Fold", "ev": 0, "color": "blue"},
    {"hand": "53s", "action": "Fold", "ev": 0, "color": "blue"},
    {"hand": "52s", "action": "Fold", "ev": 0, "color": "blue"},
    {"hand": "A4o", "action": "Fold", "ev": 0, "color": "blue"},
    {"hand": "K4o", "action": "Fold", "ev": 0, "color": "blue"},
    {"hand": "Q4o", "action": "Fold", "ev": 0, "color": "blue"},
    {"hand": "J4o", "action": "Fold", "ev": 0, "color": "blue"},
    {"hand": "T4o", "action": "Fold", "ev": 0, "color": "blue"},
    {"hand": "94o", "action": "Fold", "ev": 0, "color": "blue"},
    {"hand": "84o", "action": "Fold", "ev": 0, "color": "blue"},
    {"hand": "74o", "action": "Fold", "ev": 0, "color": "blue"},
    {"hand": "64o", "action": "Fold", "ev": 0, "color": "blue"},
    {"hand": "54o", "action": "Fold", "ev": 0, "color": "blue"},
    {"hand": "44", "action": "Fold", "ev": 0, "color": "blue"},
    {"hand": "43s", "action": "Fold", "ev": 0, "color": "blue"},
    {"hand": "42s", "action": "Fold", "ev": 0, "color": "blue"},
    {"hand": "A3o", "action": "Fold", "ev": 0, "color": "blue"},
    {"hand": "K3o", "action": "Fold", "ev": 0, "color": "blue"},
    {"hand": "Q3o", "action": "Fold", "ev": 0, "color": "blue"},
    {"hand": "J3o", "action": "Fold", "ev": 0, "color": "blue"},
    {"hand": "T3o", "action": "Fold", "ev": 0, "color": "blue"},
    {"hand": "93o", "action": "Fold", "ev": 0, "color": "blue"},
    {"hand": "83o", "action": "Fold", "ev": 0, "color": "blue"},
    {"hand": "73o", "action": "Fold", "ev": 0, "color": "blue"},
    {"hand": "63o", "action": "Fold", "ev": 0, "color": "blue"},
    {"hand": "53o", "action": "Fold", "ev": 0, "color": "blue"},
    {"hand": "43o", "action": "Fold", "ev": 0, "color": "blue"},
    {"hand": "33", "action": "Fold", "ev": 0, "color": "blue"},
    {"hand": "32s", "action": "Fold", "ev": 0, "color": "blue"},
    {"hand": "A2o", "action": "Fold", "ev": 0, "color": "blue"},
    {"hand": "K2o", "action": "Fold", "ev": 0, "color": "blue"},
    {"hand": "Q2o", "action": "Fold", "ev": 0, "color": "blue"},
    {"hand": "J2o", "action": "Fold", "ev": 0, "color": "blue"},
    {"hand": "T2o", "action": "Fold", "ev": 0, "color": "blue"},
    {"hand": "92o", "action": "Fold", "ev": 0, "color": "blue"},
    {"hand": "82o", "action": "Fold", "ev": 0, "color": "blue"},
    {"hand": "72o", "action": "Fold", "ev": 0, "color": "blue"},
    {"hand": "62o", "action": "Fold", "ev": 0, "color": "blue"},
    {"hand": "52o", "action": "Fold", "ev": 0, "color": "blue"},
    {"hand": "42o", "action": "Fold", "ev": 0, "color": "blue"},
    {"hand": "32o", "action": "Fold", "ev": 0, "color": "blue"},
    {"hand": "22", "action": "Fold", "ev": 0, "color": "blue"}
  ],
  "legend": {
    "Raise 2": {
      "color": "red",
      "percentage": 12.1,
      "combos": 39.87
    },
    "Allin 14": {
      "color": "red",
      "percentage": 3.0,
      "combos": null
    },
    "Fold": {
      "color": "blue",
      "percentage": 84.9,
      "combos": 1126.03
    }
  },
  "positions": {
    "UTG": "14",
    "UTG1": "14",
    "LJ": "14",
    "HJ": "14",
    "CO": "14",
    "BTN": "13.5",
    "SB": "13.5",
    "BB": "2.5 BB"
  }
}